dask_setup/__init__.py
dask_setup/cli.py
dask_setup/client.py
dask_setup/cluster.py
dask_setup/config.py
dask_setup/config_manager.py
dask_setup/dashboard.py
dask_setup/error_handling.py
dask_setup/exceptions.py
dask_setup/io_patterns.py
dask_setup/legacy.py
dask_setup/logging.py
dask_setup/resources.py
dask_setup/tempdir.py
dask_setup/topology.py
dask_setup/types.py
dask_setup/xarray.py
dask_setup-1.0.0.dist-info/licenses/LICENSE
dask_setup-1.0.0.dist-info/METADATA
dask_setup-1.0.0.dist-info/WHEEL
dask_setup-1.0.0.dist-info/entry_points.txt
dask_setup-1.0.0.dist-info/top_level.txt
dask_setup-1.0.0.dist-info/RECORD
