Metadata-Version: 2.4
Name: dask_setup
Version: 1.0.0
Summary: HPC-tuned Dask helpers for single-node runs on NCI Gadi.
Author: Sam Green
Project-URL: Homepage, https://github.com/21centuryweather/dask_setup
Requires-Python: >=3.11
License-File: LICENSE
Requires-Dist: dask>=2024.1.0
Requires-Dist: distributed>=2024.1.0
Requires-Dist: psutil>=5.9
Requires-Dist: pyyaml>=6.0
Provides-Extra: dev
Requires-Dist: ruff~=0.4; extra == "dev"
Requires-Dist: pytest~=8.2; extra == "dev"
Requires-Dist: pytest-cov~=5.0; extra == "dev"
Requires-Dist: xarray; extra == "dev"
Requires-Dist: numpy; extra == "dev"
Dynamic: license-file
